WeizhideShixianVol1/Dockerfile
WeizhideShixianVol1/README.md
WeizhideShixianVol1/__init__.py
WeizhideShixianVol1/__main__.py
WeizhideShixianVol1/file.epub
WeizhideShixianVol1/index.html
WeizhideShixianVol1/css/__init__.py
WeizhideShixianVol1/css/annotations.css
WeizhideShixianVol1/css/main.css
WeizhideShixianVol1/css/normalize.css
WeizhideShixianVol1/css/popup.css
WeizhideShixianVol1/font/__init__.py
WeizhideShixianVol1/font/fontello.eot
WeizhideShixianVol1/font/fontello.svg
WeizhideShixianVol1/font/fontello.ttf
WeizhideShixianVol1/font/fontello.woff
WeizhideShixianVol1/img/__init__.py
WeizhideShixianVol1/img/annotator-glyph-sprite.png
WeizhideShixianVol1/img/annotator-icon-sprite.png
WeizhideShixianVol1/img/apple-touch-icon.png
WeizhideShixianVol1/img/cancelfullscreen.png
WeizhideShixianVol1/img/close.png
WeizhideShixianVol1/img/fullscreen.png
WeizhideShixianVol1/img/loader.gif
WeizhideShixianVol1/img/menu-icon.png
WeizhideShixianVol1/img/save.png
WeizhideShixianVol1/img/saved.png
WeizhideShixianVol1/img/settings-s.png
WeizhideShixianVol1/img/settings.png
WeizhideShixianVol1/img/star.png
WeizhideShixianVol1/js/__init__.py
WeizhideShixianVol1/js/epub.js
WeizhideShixianVol1/js/epub.min.js
WeizhideShixianVol1/js/epub.min.map
WeizhideShixianVol1/js/hooks.min.js
WeizhideShixianVol1/js/hooks.min.map
WeizhideShixianVol1/js/reader.js
WeizhideShixianVol1/js/reader.js.map
WeizhideShixianVol1/js/reader.min.js
WeizhideShixianVol1/js/reader.min.map
WeizhideShixianVol1/js/hooks/__init__.py
WeizhideShixianVol1/js/hooks/extensions/__init__.py
WeizhideShixianVol1/js/hooks/extensions/highlight.js
WeizhideShixianVol1/js/libs/__init__.py
WeizhideShixianVol1/js/libs/jquery.min.js
WeizhideShixianVol1/js/libs/localforage.min.js
WeizhideShixianVol1/js/libs/screenfull.js
WeizhideShixianVol1/js/libs/screenfull.min.js
WeizhideShixianVol1/js/libs/zip.min.js
WeizhideShixianVol1/js/plugins/__init__.py
WeizhideShixianVol1/js/plugins/hypothesis.js
WeizhideShixianVol1/js/plugins/search.js
weizhide_shixian_vol1-2022.10.9.1.dist-info/METADATA
weizhide_shixian_vol1-2022.10.9.1.dist-info/WHEEL
weizhide_shixian_vol1-2022.10.9.1.dist-info/entry_points.txt
weizhide_shixian_vol1-2022.10.9.1.dist-info/top_level.txt
weizhide_shixian_vol1-2022.10.9.1.dist-info/RECORD
